{
    "isaacmedeirosal": {
        "nome": "Isaac de Medeiros",
        "idade": "20",
        "notas": {
            "bimestre1": 0,
            "bimestre2": 0
        }
    },
    "josesilvaal": {
        "nome": "Jose Bezerro da Silva",
        "idade": "20",
        "notas": {
            "bimestre1": 0,
            "bimestre2": 0
        }
    },
    "isaacmedeiros01al": {
        "nome": "Isaac de Medeiros",
        "idade": "20",
        "notas": {
            "bimestre1": 0,
            "bimestre2": 0
        }
    }
}